pynus/__init__.py
pynus/backend.py
pynus/decode.py
pynusdas-0.0.5.dist-info/LICENSE
pynusdas-0.0.5.dist-info/METADATA
pynusdas-0.0.5.dist-info/WHEEL
pynusdas-0.0.5.dist-info/entry_points.txt
pynusdas-0.0.5.dist-info/top_level.txt
pynusdas-0.0.5.dist-info/RECORD
