Metadata-Version: 2.2
Name: pynusdas
Version: 0.0.5
Summary: Python interface for the JMA's NuSDaS format
License: MIT License
Project-URL: Homepage, https://github.com/tkmim/pynus
Project-URL: Repository, https://github.com/tkmim/pynus.git
Classifier: Development Status :: 3 - Alpha
Classifier: Intended Audience :: Science/Research
Requires-Python: >=3.9
License-File: LICENSE
Requires-Dist: numpy
Requires-Dist: xarray[complete]
Requires-Dist: scipy
